gweld/__init__.py
gweld/data.py
gweld/data_set.py
gweld/vis.py
gweld/charts/__init__.py
gweld/charts/bar.py
gweld/charts/chart.py
gweld/charts/line.py
gweld/charts/pie.py
gweld/elements/__init__.py
gweld/elements/axis_element.py
gweld/elements/bg_element.py
gweld/elements/text_element.py
gweld/elements/vis_element.py
gweld/libs/__init__.py
gweld/libs/svg_lib.py
gweld/libs/util_lib.py
gweld/style/__init__.py
gweld/style/circle_text_style.py
gweld/style/style.py
gweld/style/text_style.py
gweld-0.0.3.dist-info/LICENSE
gweld-0.0.3.dist-info/METADATA
gweld-0.0.3.dist-info/WHEEL
gweld-0.0.3.dist-info/top_level.txt
gweld-0.0.3.dist-info/RECORD
